{"BluDoc.Version":"1.4.0","Created.DateTime":"2025-07-14T11:05:37.1967097+02:00","CreatorSoftware.Name":"Blumatix.BluDocConverter.LabelConverter.LabelConverter","CreatorSoftware.Version":"1.0.0.0","Document.Languages":["de"],"Document.Type":"Invoice","DocumentEssentials":[{"Items":null,"Label":"Document.Type","Location":{"Height":0,"Left":0,"Page":1,"Top":0,"Width":0},"Text":"Invoice","Value":null},{"Items":null,"Label":"Invoice.Id","Location":{"Height":28,"Left":1530,"Page":1,"Top":994,"Width":141},"Text":"2400134","Value":null},{"Items":null,"Label":"Invoice.Date","Location":{"Height":28,"Left":2161,"Page":1,"Top":994,"Width":182},"Text":"25.01.2024","Value":null},{"Items":null,"Label":"GrandTotal.Amount","Location":{"Height":33,"Left":2233,"Page":1,"Top":1852,"Width":109},"Text":"723,99","Value":null},{"Items":null,"Label":"Sender.VatId","Location":{"Height":23,"Left":2143,"Page":1,"Top":706,"Width":199},"Text":"ATU 64424288","Value":null},{"Items":[{"Items":null,"Label":"Vat.Rate","Location":{"Height":29,"Left":1633,"Page":1,"Top":1748,"Width":45},"Text":"10","Value":null},{"Items":null,"Label":"Net.Amount","Location":{"Height":33,"Left":2229,"Page":1,"Top":1691,"Width":113},"Text":"658,17","Value":null},{"Items":null,"Label":"Vat.Amount","Location":{"Height":33,"Left":2250,"Page":1,"Top":1749,"Width":91},"Text":"65,82","Value":null}],"Label":"Vat.Item","Location":null,"Text":null,"Value":null}],"DocumentProvider.Name":"Internal","Pages":[{"Dpi":300,"Height":3505,"Id":1,"Width":2480}]}